 patient_outcome_predictor/__init__.py
 patient_outcome_predictor/data_preprocessing.py
 patient_outcome_predictor/model.py
 patient_outcome_predictor/predictor.py
tests/__init__.py
tests/test_data_preprocessing.py
tests/test_model.py
tests/test_predictor.py
patient_outcome_predictor-0.1.7.dist-info/METADATA
patient_outcome_predictor-0.1.7.dist-info/WHEEL
patient_outcome_predictor-0.1.7.dist-info/top_level.txt
patient_outcome_predictor-0.1.7.dist-info/RECORD
