Metadata-Version: 2.1
Name: patient-outcome-predictor
Version: 0.1.7
Summary: A package that uses machine learning models to predict patient outcomes based on medical data.
Home-page: https://github.com/Chrispin-m/-patient_outcome_predictor
Author: iChrispin
Author-email: chrismwangicw@gmail.com
License: UNKNOWN
Platform: UNKNOWN
Classifier: Programming Language :: Python :: 3
Classifier: License :: OSI Approved :: MIT License
Classifier: Operating System :: OS Independent
Requires-Python: >=3.6
Requires-Dist: pandas
Requires-Dist: scikit-learn
Requires-Dist: numpy
Requires-Dist: streamlit
